awspice/__init__.py
awspice/helpers.py
awspice/manager.py
awspice/servicemanager.py
awspice/modules/__init__.py
awspice/modules/finder.py
awspice/modules/security.py
awspice/modules/stats.py
awspice/services/__init__.py
awspice/services/acm.py
awspice/services/base.py
awspice/services/ce.py
awspice/services/ec2.py
awspice/services/elb.py
awspice/services/iam.py
awspice/services/rds.py
awspice/services/route53.py
awspice/services/s3.py
awspice/services/_ec2/__init__.py
awspice/services/_ec2/address.py
awspice/services/_ec2/image.py
awspice/services/_ec2/instance.py
awspice/services/_ec2/security_group.py
awspice/services/_ec2/snapshot.py
awspice/services/_ec2/volume.py
awspice/services/_ec2/vpc.py
test/__init__.py
test/module_finder.py
test/module_stats.py
test/service.py
test/service_base.py
test/service_ce.py
test/service_ec2.py
test/service_elb.py
test/service_s3.py
test/test_base.py
test/test_ec2_instances.py
awspice-1.7.2.dist-info/LICENSE
awspice-1.7.2.dist-info/METADATA
awspice-1.7.2.dist-info/WHEEL
awspice-1.7.2.dist-info/top_level.txt
awspice-1.7.2.dist-info/RECORD
