Metadata-Version: 2.1
Name: awspice
Version: 1.7.2
Summary: Awspice is a wrapper tool of Boto3 library to list inventory and manage your AWS infrastructure The objective of the wrapper is to abstract the use of AWS, being able to dig through all the data of our account. It belongs to ElevenPaths, Telefonica.
Home-page: https://github.com/davidmoremad
Author: David Amrani Hernandez
Author-email: davidmorenomad@gmail.com
License: Apache 2.0
Project-URL: Source Code, https://github.com/Telefonica/awspice
Project-URL: Documentation, https://awspice.readthedocs.io
Keywords: aws amazon cloud platform boto3 wrapper security management region account
Platform: UNKNOWN
Classifier: Development Status :: 4 - Beta
Classifier: Intended Audience :: Developers
Classifier: Intended Audience :: Other Audience
Classifier: License :: OSI Approved :: Apache Software License
Classifier: Natural Language :: English
Classifier: Operating System :: OS Independent
Classifier: Programming Language :: Python :: 2.7
Classifier: Programming Language :: Python :: 3.3
Classifier: Programming Language :: Python :: 3.4
Classifier: Programming Language :: Python :: 3.5
Classifier: Topic :: Software Development :: Libraries :: Python Modules
Classifier: Topic :: Software Development :: Quality Assurance
Classifier: Topic :: Software Development :: Testing
Requires-Dist: boto3 (==1.5.11)
Requires-Dist: dnspython (==1.15.0)
